graze/__init__.py
graze/_britannica.py
graze/_freesound.py
graze/_pexels.py
graze/_transcripts.py
graze/_unsplash.py
graze/_wiki.py
graze/queries.py
graze/topics.json
webgraze-1.1.3.dist-info/licenses/LICENSE
webgraze-1.1.3.dist-info/METADATA
webgraze-1.1.3.dist-info/WHEEL
webgraze-1.1.3.dist-info/top_level.txt
webgraze-1.1.3.dist-info/RECORD
