Metadata-Version: 2.4
Name: webgraze
Version: 1.1.3
Summary: WebScraping library that scrapes & gathers data from multiple sources on the internet
Author-email: shivendra <shivharsh44@gmail.com>
Maintainer-email: shivendra <shivharsh44@gmail.com>
License: MIT
Project-URL: Homepage, https://github.com/shivendrra/web-graze
Project-URL: Repository, https://github.com/shivendrra/web-graze
Project-URL: Documentation, https://github.com/shivendrra/web-graze/tree/main/docs
Project-URL: Issues, https://github.com/shivendra/webg-raze/issues
Keywords: webscraping,scraping,webscraping library,web scraping,python webscraping,beautifulsoup,selenium,data collection,web automation
Classifier: Development Status :: 4 - Beta
Classifier: Intended Audience :: Developers
Classifier: License :: OSI Approved :: MIT License
Classifier: Programming Language :: Python
Classifier: Programming Language :: Python :: 3.8
Classifier: Programming Language :: Python :: 3.9
Classifier: Programming Language :: Python :: 3.10
Classifier: Programming Language :: Python :: 3.11
Classifier: Programming Language :: Python :: 3.12
Classifier: Topic :: Internet :: WWW/HTTP :: Browsers
Classifier: Topic :: Software Development :: Libraries :: Python Modules
Classifier: Topic :: Text Processing :: Markup :: HTML
Classifier: Operating System :: OS Independent
Requires-Python: >=3.8
License-File: LICENSE
Requires-Dist: beautifulsoup4>=4.11.0
Requires-Dist: tqdm>=4.64.0
Requires-Dist: google-api-python-client>=2.70.0
Requires-Dist: requests>=2.28.0
Requires-Dist: youtube-transcript-api>=0.6.0
Requires-Dist: selenium>=4.15.0
Requires-Dist: webdriver-manager>=4.0.0
Requires-Dist: lxml>=4.9.0
Provides-Extra: dev
Requires-Dist: pytest>=7.0.0; extra == "dev"
Requires-Dist: pytest-cov>=4.0.0; extra == "dev"
Requires-Dist: black>=22.0.0; extra == "dev"
Requires-Dist: flake8>=5.0.0; extra == "dev"
Requires-Dist: mypy>=1.0.0; extra == "dev"
Requires-Dist: pre-commit>=2.20.0; extra == "dev"
Provides-Extra: docs
Requires-Dist: sphinx>=5.0.0; extra == "docs"
Requires-Dist: sphinx-rtd-theme>=1.2.0; extra == "docs"
Requires-Dist: myst-parser>=0.18.0; extra == "docs"
Provides-Extra: testing
Requires-Dist: pytest>=7.0.0; extra == "testing"
Requires-Dist: pytest-mock>=3.10.0; extra == "testing"
Requires-Dist: responses>=0.22.0; extra == "testing"
Requires-Dist: pytest-asyncio>=0.21.0; extra == "testing"
Dynamic: license-file
